clipkit/__init__.py
clipkit/__main__.py
clipkit/api.py
clipkit/args_processing.py
clipkit/clipkit.py
clipkit/exceptions.py
clipkit/files.py
clipkit/helpers.py
clipkit/logger.py
clipkit/modes.py
clipkit/msa.py
clipkit/parser.py
clipkit/settings.py
clipkit/site_classification.py
clipkit/smart_gap_helper.py
clipkit/stats.py
clipkit/version.py
clipkit/warnings.py
clipkit/write.py
clipkit-2.7.0.dist-info/LICENSE.md
clipkit-2.7.0.dist-info/METADATA
clipkit-2.7.0.dist-info/WHEEL
clipkit-2.7.0.dist-info/entry_points.txt
clipkit-2.7.0.dist-info/top_level.txt
clipkit-2.7.0.dist-info/RECORD
