Metadata-Version: 2.1
Name: clipkit
Version: 2.7.0
Summary: Alignment trimming software for phylogenetics.
Home-page: https://github.com/jlsteenwyk/clipkit
Author: Jacob L. Steenwyk
Author-email: jlsteenwyk@gmail.com
Classifier: Operating System :: OS Independent
Classifier: Intended Audience :: Science/Research
Classifier: Programming Language :: Python
Classifier: Programming Language :: Python :: 3.9
Classifier: Programming Language :: Python :: 3.10
Classifier: Programming Language :: Python :: 3.11
Classifier: Programming Language :: Python :: 3.12
Classifier: Programming Language :: Python :: 3.13
Classifier: Topic :: Scientific/Engineering
Requires-Python: >=3.9
License-File: LICENSE.md
Requires-Dist: numpy (<2.0,>=1.24.0) ; python_version < "3.12"
Requires-Dist: biopython (>=1.82) ; python_version < "3.13"
Requires-Dist: numpy (<2.1,>=1.26.0) ; python_version == "3.12"
Requires-Dist: biopython (>=1.84) ; python_version >= "3.13"
Requires-Dist: numpy (<2.2,>=2.0.0) ; python_version >= "3.13"
